versioned_classes/__init__.py
versioned_classes/versioned_class.py
versioned_classes/versioning_format.py
versioned_classes-0.0.1.dist-info/LICENSE
versioned_classes-0.0.1.dist-info/WHEEL
versioned_classes-0.0.1.dist-info/METADATA
versioned_classes-0.0.1.dist-info/RECORD
