Metadata-Version: 2.1
Name: versioned-classes
Version: 0.0.1
Summary: A simple library for managing versioning of classes
Keywords: versioning,version,versioner,versioning classes,versioning objects
Author-email: Declan Atkins <declanatkins@gmail.com>
Requires-Python: >=3.7
Classifier: Programming Language :: Python :: 3
Classifier: License :: OSI Approved :: MIT License
Classifier: Operating System :: OS Independent
